{
  "https://streaming.radio.co/s3699c5e49/listen": { "tags": ["electronic", "community", "eclectic"], "group": "community" },
  "https://listen.radioking.com/radio/282820/stream/328621": { "tags": ["experimental", "electronic", "folk", "eclectic"], "group": "experimental" },
  "https://radio80k.out.airtime.pro:8000/radio80k_a": { "tags": ["eclectic", "community"], "group": "community" },
  "https://kexp.streamguys1.com/kexp160.aac": { "tags": ["rock", "indie", "electronic", "eclectic", "community"], "group": "eclectic" },
  "https://kexp.streamguys1.com/kexp64.aac": { "tags": ["rock", "indie", "electronic", "eclectic", "community"], "group": "eclectic" },
  "https://ice5.somafm.com/live-128-mp3": { "tags": ["electronic", "ambient", "eclectic", "community"], "group": "eclectic" },
  "https://ice5.somafm.com/groovesalad-128-mp3": { "tags": ["electronic", "ambient", "eclectic", "community"], "group": "eclectic" },
  "https://ice5.somafm.com/dronezone-128-mp3": { "tags": ["electronic", "ambient", "eclectic", "community"], "group": "eclectic" },
  "https://ice5.somafm.com/spacestation-128-mp3": { "tags": ["electronic", "ambient", "eclectic", "community"], "group": "eclectic" },
  "https://ice5.somafm.com/lush-128-mp3": { "tags": ["electronic", "ambient", "eclectic", "community"], "group": "eclectic" },
  "https://ice5.somafm.com/defcon-128-mp3": { "tags": ["electronic", "ambient", "eclectic", "community"], "group": "eclectic" },
  "https://ice5.somafm.com/covers-128-mp3": { "tags": ["electronic", "ambient", "eclectic", "community"], "group": "eclectic" },
  "https://ice5.somafm.com/indiepop-128-mp3": { "tags": ["electronic", "ambient", "eclectic", "community"], "group": "eclectic" },
  "http://stream0.wfmu.org/freeform-128k": { "tags": ["freeform", "eclectic", "community"], "group": "eclectic" },
  "http://stream0.wfmu.org/rock-128k": { "tags": ["freeform", "eclectic", "community"], "group": "eclectic" },
  "http://stream0.wfmu.org/drummer-128k": { "tags": ["freeform", "eclectic", "community"], "group": "eclectic" },
  "http://stream0.wfmu.org/sheena-128k": { "tags": ["freeform", "eclectic", "community"], "group": "eclectic" },
  "https://stream-relay-geo.ntslive.net/stream": { "tags": ["electronic", "eclectic", "community"], "group": "eclectic" },
  "https://stream-relay-geo.ntslive.net/stream2": { "tags": ["electronic", "eclectic", "community"], "group": "eclectic" },
  "https://stream.lyl.live/live": { "tags": ["electronic", "eclectic", "community"], "group": "community" },
  "https://stream.noodsradio.com/stream": { "tags": ["electronic", "dub", "experimental"], "group": "electronic" },
  "https://veneno.out.airtime.pro/veneno_a": { "tags": ["electronic", "house", "techno", "world"], "group": "electronic" },
  "https://kioskradiobxl.out.airtime.pro/kioskradiobxl_b": { "tags": ["electronic", "eclectic", "community"], "group": "community" },
  "http://stream.kchungradio.org:8000/stream": { "tags": ["community", "eclectic"], "group": "community" },
  "https://stream.tikka.live/live": { "tags": ["eclectic"], "group": "other" },
  "https://wobc.stream/stream": { "tags": ["college", "freeform"], "group": "college" },
  "https://stream.particle.fm/live": { "tags": ["electronic", "community", "eclectic"], "group": "community" },
  "https://stream.hopestradio.community/live": { "tags": ["community", "eclectic"], "group": "community" },
  "https://netilradio.out.airtime.pro/netilradio_b": { "tags": ["electronic", "community"], "group": "community" },
  "https://tsubakifm.out.airtime.pro/tsubakifm_a": { "tags": ["jazz", "soul", "electronic", "disco", "world"], "group": "eclectic" },
  "https://radionopal.out.airtime.pro/radionopal_a": { "tags": ["community", "eclectic"], "group": "community" },
  "https://radio.goodtimesbadtimes.club/radio/8000/radio.mp3": { "tags": ["community", "eclectic"], "group": "community" },
  "https://radio.robidacollective.com/stream/programme": { "tags": ["ambient", "experimental", "community"], "group": "experimental" },
  "https://yamakan.out.airtime.pro/yamakan_a": { "tags": ["community", "world"], "group": "community" },
  "http://streams.movemedia.eu/centraal": { "tags": ["eclectic", "community", "arts"], "group": "community" },
  "https://stream.radiocult.fm/area-3000": { "tags": ["electronic", "community"], "group": "electronic" },
  "https://cashmereradio.out.airtime.pro/cashmereradio_b": { "tags": ["experimental", "electronic", "ambient"], "group": "experimental" },
  "https://stream.radiocampus.be/stream": { "tags": ["jazz", "rock", "electronic", "college"], "group": "college" },
  "https://blackrhinoradio.out.airtime.pro/blackrhinoradio_a": { "tags": ["electronic", "dub", "jazz", "hiphop"], "group": "electronic" },
  "https://stream4.rcast.net/72355/": { "tags": ["rock", "electronic", "indie"], "group": "eclectic" },
  "https://dublab.out.airtime.pro/dublab_a": { "tags": ["experimental", "electronic", "jazz", "hiphop", "dub"], "group": "eclectic" },
  "https://rukh.out.airtime.pro/rukh_a": { "tags": ["experimental", "community"], "group": "experimental" },
  "https://live.helsinki.at:8088/live160.mp3": { "tags": ["community", "eclectic"], "group": "community" },
  "https://stream.hkcr.live/stream": { "tags": ["community", "eclectic"], "group": "community" },
  "https://n02.radiojar.com/78cxy6wkxtzuv": { "tags": ["community", "world", "experimental"], "group": "community" },
  "https://thelakeradio.out.airtime.pro/thelakeradio_a": { "tags": ["experimental", "arts"], "group": "experimental" },
  "http://anonradio.net:8000/anonradio": { "tags": ["experimental", "community", "eclectic"], "group": "experimental" },
  "http://213.133.109.221:8205/dfm_1": { "tags": ["experimental", "electronic"], "group": "experimental" },
  "https://s3.radio.co/sb713b671e/listen": { "tags": ["electronic", "community", "eclectic"], "group": "community" },
  "http://104.63.241.231:8000/listen": { "tags": ["community", "eclectic"], "group": "community" },
  "http://stream.resonance.fm:8000/resonance": { "tags": ["arts", "experimental", "community"], "group": "arts" },
  "http://stream.resonance.fm:8000/resonance-extra": { "tags": ["arts", "experimental", "community"], "group": "arts" },
  "https://flujos.mazorca.org/violetaradio.mp3": { "tags": ["feminist", "community"], "group": "community" }
}
